ebi/__init__.py
ebi/ebi.cpython-313t-arm-linux-musleabihf.so
ebi.libs/libgcc_s-262c4f60.so.1
ebi_pm-0.3.9.dist-info/METADATA
ebi_pm-0.3.9.dist-info/WHEEL
ebi_pm-0.3.9.dist-info/RECORD
