Metadata-Version: 2.4
Name: ebi-pm
Version: 0.3.9
Requires-Dist: pm4py
Summary: Ebi: a stochastic process mining utility
Keywords: process mining,stochastic process mining,business process analysis
Home-Page: https://ebitools.org
Author: Sander Leemans, Tian Li, Philipp Moch, Leonhard Mühlmeyer, Adam Burke
